luminoso_api/__init__.py
luminoso_api/client.py
luminoso_api/compat.py
luminoso_api/errors.py
luminoso_api/v4_auth.py
luminoso_api/v4_client.py
luminoso_api/v4_constants.py
luminoso_api/v4_json_stream.py
luminoso_api/v4_upload.py
luminoso_api/v5_cli.py
luminoso_api/v5_client.py
luminoso_api/v5_constants.py
luminoso_api-1.0.1.dist-info/METADATA
luminoso_api-1.0.1.dist-info/RECORD
luminoso_api-1.0.1.dist-info/WHEEL
luminoso_api-1.0.1.dist-info/entry_points.txt
luminoso_api-1.0.1.dist-info/top_level.txt
