Metadata-Version: 2.1
Name: luminoso-api
Version: 1.0.1
Summary: Python client library for communicating with the Luminoso REST API
Home-page: http://github.com/LuminosoInsight/luminoso-api-client-python
Maintainer: Luminoso Technologies, Inc.
Maintainer-email: info@luminoso.com
License: UNKNOWN
Download-URL: http://github.com/LuminosoInsight/luminoso-api-client-python/tarball/v1.0.1
Platform: any
Classifier: Intended Audience :: Developers
Classifier: Intended Audience :: Science/Research
Classifier: Natural Language :: English
Classifier: Topic :: Scientific/Engineering
Classifier: Topic :: Text Processing :: Linguistic
Requires-Dist: requests (<3.0,>=1.2.1)
Requires-Dist: ftfy (>=5)
